{"nodes": [{"id": "c_users_marce_onedrive_desktop_projetos_web_loja_rataplam_modules_banner_models_banner_php", "label": "Banner.php", "file_type": "code", "source_file": "C:\\Users\\marce\\OneDrive\\Desktop\\PROJETOS WEB\\LOJA RATAPLAM\\Modules\\Banner\\Models\\Banner.php", "source_location": "L1"}, {"id": "models_banner_banner", "label": "Banner", "file_type": "code", "source_file": "C:\\Users\\marce\\OneDrive\\Desktop\\PROJETOS WEB\\LOJA RATAPLAM\\Modules\\Banner\\Models\\Banner.php", "source_location": "L65"}, {"id": "models_banner_banner_factory", "label": ".Factory()", "file_type": "code", "source_file": "C:\\Users\\marce\\OneDrive\\Desktop\\PROJETOS WEB\\LOJA RATAPLAM\\Modules\\Banner\\Models\\Banner.php", "source_location": "L87"}, {"id": "models_banner_banner_getimageurlattribute", "label": ".getImageUrlAttribute()", "file_type": "code", "source_file": "C:\\Users\\marce\\OneDrive\\Desktop\\PROJETOS WEB\\LOJA RATAPLAM\\Modules\\Banner\\Models\\Banner.php", "source_location": "L92"}, {"id": "models_banner_banner_categories", "label": ".categories()", "file_type": "code", "source_file": "C:\\Users\\marce\\OneDrive\\Desktop\\PROJETOS WEB\\LOJA RATAPLAM\\Modules\\Banner\\Models\\Banner.php", "source_location": "L109"}, {"id": "models_banner_banner_scopeactive", "label": ".scopeActive()", "file_type": "code", "source_file": "C:\\Users\\marce\\OneDrive\\Desktop\\PROJETOS WEB\\LOJA RATAPLAM\\Modules\\Banner\\Models\\Banner.php", "source_location": "L120"}, {"id": "models_banner_banner_isactive", "label": ".isActive()", "file_type": "code", "source_file": "C:\\Users\\marce\\OneDrive\\Desktop\\PROJETOS WEB\\LOJA RATAPLAM\\Modules\\Banner\\Models\\Banner.php", "source_location": "L143"}, {"id": "models_banner_banner_incrementimpression", "label": ".incrementImpression()", "file_type": "code", "source_file": "C:\\Users\\marce\\OneDrive\\Desktop\\PROJETOS WEB\\LOJA RATAPLAM\\Modules\\Banner\\Models\\Banner.php", "source_location": "L168"}, {"id": "models_banner_banner_incrementclick", "label": ".incrementClick()", "file_type": "code", "source_file": "C:\\Users\\marce\\OneDrive\\Desktop\\PROJETOS WEB\\LOJA RATAPLAM\\Modules\\Banner\\Models\\Banner.php", "source_location": "L179"}], "edges": [{"source": "c_users_marce_onedrive_desktop_projetos_web_loja_rataplam_modules_banner_models_banner_php", "target": "eloquent", "relation": "imports", "context": "import", "confidence": "EXTRACTED", "source_file": "C:\\Users\\marce\\OneDrive\\Desktop\\PROJETOS WEB\\LOJA RATAPLAM\\Modules\\Banner\\Models\\Banner.php", "source_location": "L11", "weight": 1.0}, {"source": "c_users_marce_onedrive_desktop_projetos_web_loja_rataplam_modules_banner_models_banner_php", "target": "builder", "relation": "imports", "context": "import", "confidence": "EXTRACTED", "source_file": "C:\\Users\\marce\\OneDrive\\Desktop\\PROJETOS WEB\\LOJA RATAPLAM\\Modules\\Banner\\Models\\Banner.php", "source_location": "L12", "weight": 1.0}, {"source": "c_users_marce_onedrive_desktop_projetos_web_loja_rataplam_modules_banner_models_banner_php", "target": "collection", "relation": "imports", "context": "import", "confidence": "EXTRACTED", "source_file": "C:\\Users\\marce\\OneDrive\\Desktop\\PROJETOS WEB\\LOJA RATAPLAM\\Modules\\Banner\\Models\\Banner.php", "source_location": "L13", "weight": 1.0}, {"source": "c_users_marce_onedrive_desktop_projetos_web_loja_rataplam_modules_banner_models_banner_php", "target": "hasfactory", "relation": "imports", "context": "import", "confidence": "EXTRACTED", "source_file": "C:\\Users\\marce\\OneDrive\\Desktop\\PROJETOS WEB\\LOJA RATAPLAM\\Modules\\Banner\\Models\\Banner.php", "source_location": "L14", "weight": 1.0}, {"source": "c_users_marce_onedrive_desktop_projetos_web_loja_rataplam_modules_banner_models_banner_php", "target": "carbon", "relation": "imports", "context": "import", "confidence": "EXTRACTED", "source_file": "C:\\Users\\marce\\OneDrive\\Desktop\\PROJETOS WEB\\LOJA RATAPLAM\\Modules\\Banner\\Models\\Banner.php", "source_location": "L15", "weight": 1.0}, {"source": "c_users_marce_onedrive_desktop_projetos_web_loja_rataplam_modules_banner_models_banner_php", "target": "bannerfactory", "relation": "imports", "context": "import", "confidence": "EXTRACTED", "source_file": "C:\\Users\\marce\\OneDrive\\Desktop\\PROJETOS WEB\\LOJA RATAPLAM\\Modules\\Banner\\Models\\Banner.php", "source_location": "L16", "weight": 1.0}, {"source": "c_users_marce_onedrive_desktop_projetos_web_loja_rataplam_modules_banner_models_banner_php", "target": "category", "relation": "imports", "context": "import", "confidence": "EXTRACTED", "source_file": "C:\\Users\\marce\\OneDrive\\Desktop\\PROJETOS WEB\\LOJA RATAPLAM\\Modules\\Banner\\Models\\Banner.php", "source_location": "L17", "weight": 1.0}, {"source": "c_users_marce_onedrive_desktop_projetos_web_loja_rataplam_modules_banner_models_banner_php", "target": "core", "relation": "imports", "context": "import", "confidence": "EXTRACTED", "source_file": "C:\\Users\\marce\\OneDrive\\Desktop\\PROJETOS WEB\\LOJA RATAPLAM\\Modules\\Banner\\Models\\Banner.php", "source_location": "L18", "weight": 1.0}, {"source": "c_users_marce_onedrive_desktop_projetos_web_loja_rataplam_modules_banner_models_banner_php", "target": "hasslug", "relation": "imports", "context": "import", "confidence": "EXTRACTED", "source_file": "C:\\Users\\marce\\OneDrive\\Desktop\\PROJETOS WEB\\LOJA RATAPLAM\\Modules\\Banner\\Models\\Banner.php", "source_location": "L19", "weight": 1.0}, {"source": "c_users_marce_onedrive_desktop_projetos_web_loja_rataplam_modules_banner_models_banner_php", "target": "hasmedia", "relation": "imports", "context": "import", "confidence": "EXTRACTED", "source_file": "C:\\Users\\marce\\OneDrive\\Desktop\\PROJETOS WEB\\LOJA RATAPLAM\\Modules\\Banner\\Models\\Banner.php", "source_location": "L20", "weight": 1.0}, {"source": "c_users_marce_onedrive_desktop_projetos_web_loja_rataplam_modules_banner_models_banner_php", "target": "interactswithmedia", "relation": "imports", "context": "import", "confidence": "EXTRACTED", "source_file": "C:\\Users\\marce\\OneDrive\\Desktop\\PROJETOS WEB\\LOJA RATAPLAM\\Modules\\Banner\\Models\\Banner.php", "source_location": "L21", "weight": 1.0}, {"source": "c_users_marce_onedrive_desktop_projetos_web_loja_rataplam_modules_banner_models_banner_php", "target": "mediacollection", "relation": "imports", "context": "import", "confidence": "EXTRACTED", "source_file": "C:\\Users\\marce\\OneDrive\\Desktop\\PROJETOS WEB\\LOJA RATAPLAM\\Modules\\Banner\\Models\\Banner.php", "source_location": "L22", "weight": 1.0}, {"source": "c_users_marce_onedrive_desktop_projetos_web_loja_rataplam_modules_banner_models_banner_php", "target": "media", "relation": "imports", "context": "import", "confidence": "EXTRACTED", "source_file": "C:\\Users\\marce\\OneDrive\\Desktop\\PROJETOS WEB\\LOJA RATAPLAM\\Modules\\Banner\\Models\\Banner.php", "source_location": "L23", "weight": 1.0}, {"source": "c_users_marce_onedrive_desktop_projetos_web_loja_rataplam_modules_banner_models_banner_php", "target": "models_banner_banner", "relation": "contains", "confidence": "EXTRACTED", "source_file": "C:\\Users\\marce\\OneDrive\\Desktop\\PROJETOS WEB\\LOJA RATAPLAM\\Modules\\Banner\\Models\\Banner.php", "source_location": "L65", "weight": 1.0}, {"source": "models_banner_banner", "target": "models_banner_banner_factory", "relation": "method", "confidence": "EXTRACTED", "source_file": "C:\\Users\\marce\\OneDrive\\Desktop\\PROJETOS WEB\\LOJA RATAPLAM\\Modules\\Banner\\Models\\Banner.php", "source_location": "L87", "weight": 1.0}, {"source": "models_banner_banner", "target": "models_banner_banner_getimageurlattribute", "relation": "method", "confidence": "EXTRACTED", "source_file": "C:\\Users\\marce\\OneDrive\\Desktop\\PROJETOS WEB\\LOJA RATAPLAM\\Modules\\Banner\\Models\\Banner.php", "source_location": "L92", "weight": 1.0}, {"source": "models_banner_banner", "target": "models_banner_banner_categories", "relation": "method", "confidence": "EXTRACTED", "source_file": "C:\\Users\\marce\\OneDrive\\Desktop\\PROJETOS WEB\\LOJA RATAPLAM\\Modules\\Banner\\Models\\Banner.php", "source_location": "L109", "weight": 1.0}, {"source": "models_banner_banner", "target": "models_banner_banner_scopeactive", "relation": "method", "confidence": "EXTRACTED", "source_file": "C:\\Users\\marce\\OneDrive\\Desktop\\PROJETOS WEB\\LOJA RATAPLAM\\Modules\\Banner\\Models\\Banner.php", "source_location": "L120", "weight": 1.0}, {"source": "models_banner_banner", "target": "models_banner_banner_isactive", "relation": "method", "confidence": "EXTRACTED", "source_file": "C:\\Users\\marce\\OneDrive\\Desktop\\PROJETOS WEB\\LOJA RATAPLAM\\Modules\\Banner\\Models\\Banner.php", "source_location": "L143", "weight": 1.0}, {"source": "models_banner_banner", "target": "models_banner_banner_incrementimpression", "relation": "method", "confidence": "EXTRACTED", "source_file": "C:\\Users\\marce\\OneDrive\\Desktop\\PROJETOS WEB\\LOJA RATAPLAM\\Modules\\Banner\\Models\\Banner.php", "source_location": "L168", "weight": 1.0}, {"source": "models_banner_banner", "target": "models_banner_banner_incrementclick", "relation": "method", "confidence": "EXTRACTED", "source_file": "C:\\Users\\marce\\OneDrive\\Desktop\\PROJETOS WEB\\LOJA RATAPLAM\\Modules\\Banner\\Models\\Banner.php", "source_location": "L179", "weight": 1.0}], "raw_calls": [{"caller_nid": "models_banner_banner_factory", "callee": "BannerFactory", "is_member_call": false, "source_file": "C:\\Users\\marce\\OneDrive\\Desktop\\PROJETOS WEB\\LOJA RATAPLAM\\Modules\\Banner\\Models\\Banner.php", "source_location": "L89"}, {"caller_nid": "models_banner_banner_getimageurlattribute", "callee": "getFirstMedia", "is_member_call": true, "source_file": "C:\\Users\\marce\\OneDrive\\Desktop\\PROJETOS WEB\\LOJA RATAPLAM\\Modules\\Banner\\Models\\Banner.php", "source_location": "L94"}, {"caller_nid": "models_banner_banner_getimageurlattribute", "callee": "getUrl", "is_member_call": true, "source_file": "C:\\Users\\marce\\OneDrive\\Desktop\\PROJETOS WEB\\LOJA RATAPLAM\\Modules\\Banner\\Models\\Banner.php", "source_location": "L97"}, {"caller_nid": "models_banner_banner_getimageurlattribute", "callee": "route", "is_member_call": false, "source_file": "C:\\Users\\marce\\OneDrive\\Desktop\\PROJETOS WEB\\LOJA RATAPLAM\\Modules\\Banner\\Models\\Banner.php", "source_location": "L100"}, {"caller_nid": "models_banner_banner_getimageurlattribute", "callee": "\\Illuminate\\Support\\Str", "is_member_call": false, "source_file": "C:\\Users\\marce\\OneDrive\\Desktop\\PROJETOS WEB\\LOJA RATAPLAM\\Modules\\Banner\\Models\\Banner.php", "source_location": "L102"}, {"caller_nid": "models_banner_banner_categories", "callee": "belongsToMany", "is_member_call": true, "source_file": "C:\\Users\\marce\\OneDrive\\Desktop\\PROJETOS WEB\\LOJA RATAPLAM\\Modules\\Banner\\Models\\Banner.php", "source_location": "L111"}, {"caller_nid": "models_banner_banner_scopeactive", "callee": "now", "is_member_call": false, "source_file": "C:\\Users\\marce\\OneDrive\\Desktop\\PROJETOS WEB\\LOJA RATAPLAM\\Modules\\Banner\\Models\\Banner.php", "source_location": "L122"}, {"caller_nid": "models_banner_banner_scopeactive", "callee": "where", "is_member_call": true, "source_file": "C:\\Users\\marce\\OneDrive\\Desktop\\PROJETOS WEB\\LOJA RATAPLAM\\Modules\\Banner\\Models\\Banner.php", "source_location": "L124"}, {"caller_nid": "models_banner_banner_scopeactive", "callee": "where", "is_member_call": true, "source_file": "C:\\Users\\marce\\OneDrive\\Desktop\\PROJETOS WEB\\LOJA RATAPLAM\\Modules\\Banner\\Models\\Banner.php", "source_location": "L124"}, {"caller_nid": "models_banner_banner_scopeactive", "callee": "where", "is_member_call": true, "source_file": "C:\\Users\\marce\\OneDrive\\Desktop\\PROJETOS WEB\\LOJA RATAPLAM\\Modules\\Banner\\Models\\Banner.php", "source_location": "L124"}, {"caller_nid": "models_banner_banner_scopeactive", "callee": "where", "is_member_call": true, "source_file": "C:\\Users\\marce\\OneDrive\\Desktop\\PROJETOS WEB\\LOJA RATAPLAM\\Modules\\Banner\\Models\\Banner.php", "source_location": "L124"}, {"caller_nid": "models_banner_banner_scopeactive", "callee": "where", "is_member_call": true, "source_file": "C:\\Users\\marce\\OneDrive\\Desktop\\PROJETOS WEB\\LOJA RATAPLAM\\Modules\\Banner\\Models\\Banner.php", "source_location": "L124"}, {"caller_nid": "models_banner_banner_scopeactive", "callee": "orWhere", "is_member_call": true, "source_file": "C:\\Users\\marce\\OneDrive\\Desktop\\PROJETOS WEB\\LOJA RATAPLAM\\Modules\\Banner\\Models\\Banner.php", "source_location": "L127"}, {"caller_nid": "models_banner_banner_scopeactive", "callee": "whereNull", "is_member_call": true, "source_file": "C:\\Users\\marce\\OneDrive\\Desktop\\PROJETOS WEB\\LOJA RATAPLAM\\Modules\\Banner\\Models\\Banner.php", "source_location": "L127"}, {"caller_nid": "models_banner_banner_scopeactive", "callee": "orWhere", "is_member_call": true, "source_file": "C:\\Users\\marce\\OneDrive\\Desktop\\PROJETOS WEB\\LOJA RATAPLAM\\Modules\\Banner\\Models\\Banner.php", "source_location": "L130"}, {"caller_nid": "models_banner_banner_scopeactive", "callee": "whereNull", "is_member_call": true, "source_file": "C:\\Users\\marce\\OneDrive\\Desktop\\PROJETOS WEB\\LOJA RATAPLAM\\Modules\\Banner\\Models\\Banner.php", "source_location": "L130"}, {"caller_nid": "models_banner_banner_scopeactive", "callee": "orWhereColumn", "is_member_call": true, "source_file": "C:\\Users\\marce\\OneDrive\\Desktop\\PROJETOS WEB\\LOJA RATAPLAM\\Modules\\Banner\\Models\\Banner.php", "source_location": "L133"}, {"caller_nid": "models_banner_banner_scopeactive", "callee": "whereNull", "is_member_call": true, "source_file": "C:\\Users\\marce\\OneDrive\\Desktop\\PROJETOS WEB\\LOJA RATAPLAM\\Modules\\Banner\\Models\\Banner.php", "source_location": "L133"}, {"caller_nid": "models_banner_banner_scopeactive", "callee": "orWhereColumn", "is_member_call": true, "source_file": "C:\\Users\\marce\\OneDrive\\Desktop\\PROJETOS WEB\\LOJA RATAPLAM\\Modules\\Banner\\Models\\Banner.php", "source_location": "L136"}, {"caller_nid": "models_banner_banner_scopeactive", "callee": "whereNull", "is_member_call": true, "source_file": "C:\\Users\\marce\\OneDrive\\Desktop\\PROJETOS WEB\\LOJA RATAPLAM\\Modules\\Banner\\Models\\Banner.php", "source_location": "L136"}, {"caller_nid": "models_banner_banner_isactive", "callee": "now", "is_member_call": false, "source_file": "C:\\Users\\marce\\OneDrive\\Desktop\\PROJETOS WEB\\LOJA RATAPLAM\\Modules\\Banner\\Models\\Banner.php", "source_location": "L145"}, {"caller_nid": "models_banner_banner_isactive", "callee": "lt", "is_member_call": true, "source_file": "C:\\Users\\marce\\OneDrive\\Desktop\\PROJETOS WEB\\LOJA RATAPLAM\\Modules\\Banner\\Models\\Banner.php", "source_location": "L149"}, {"caller_nid": "models_banner_banner_isactive", "callee": "gt", "is_member_call": true, "source_file": "C:\\Users\\marce\\OneDrive\\Desktop\\PROJETOS WEB\\LOJA RATAPLAM\\Modules\\Banner\\Models\\Banner.php", "source_location": "L152"}, {"caller_nid": "models_banner_banner_incrementimpression", "callee": "increment", "is_member_call": true, "source_file": "C:\\Users\\marce\\OneDrive\\Desktop\\PROJETOS WEB\\LOJA RATAPLAM\\Modules\\Banner\\Models\\Banner.php", "source_location": "L170"}, {"caller_nid": "models_banner_banner_incrementimpression", "callee": "update", "is_member_call": true, "source_file": "C:\\Users\\marce\\OneDrive\\Desktop\\PROJETOS WEB\\LOJA RATAPLAM\\Modules\\Banner\\Models\\Banner.php", "source_location": "L172"}, {"caller_nid": "models_banner_banner_incrementclick", "callee": "increment", "is_member_call": true, "source_file": "C:\\Users\\marce\\OneDrive\\Desktop\\PROJETOS WEB\\LOJA RATAPLAM\\Modules\\Banner\\Models\\Banner.php", "source_location": "L181"}, {"caller_nid": "models_banner_banner_incrementclick", "callee": "update", "is_member_call": true, "source_file": "C:\\Users\\marce\\OneDrive\\Desktop\\PROJETOS WEB\\LOJA RATAPLAM\\Modules\\Banner\\Models\\Banner.php", "source_location": "L183"}]}