{"nodes": [{"id": "c_users_marce_onedrive_desktop_projetos_web_loja_rataplam_modules_core_traits_apipaginationtrait_php", "label": "ApiPaginationTrait.php", "file_type": "code", "source_file": "C:\\Users\\marce\\OneDrive\\Desktop\\PROJETOS WEB\\LOJA RATAPLAM\\Modules\\Core\\Traits\\ApiPaginationTrait.php", "source_location": "L1"}, {"id": "traits_apipaginationtrait_paginatequery", "label": "paginateQuery()", "file_type": "code", "source_file": "C:\\Users\\marce\\OneDrive\\Desktop\\PROJETOS WEB\\LOJA RATAPLAM\\Modules\\Core\\Traits\\ApiPaginationTrait.php", "source_location": "L16"}, {"id": "traits_apipaginationtrait_getperpage", "label": "getPerPage()", "file_type": "code", "source_file": "C:\\Users\\marce\\OneDrive\\Desktop\\PROJETOS WEB\\LOJA RATAPLAM\\Modules\\Core\\Traits\\ApiPaginationTrait.php", "source_location": "L27"}, {"id": "traits_apipaginationtrait_getpage", "label": "getPage()", "file_type": "code", "source_file": "C:\\Users\\marce\\OneDrive\\Desktop\\PROJETOS WEB\\LOJA RATAPLAM\\Modules\\Core\\Traits\\ApiPaginationTrait.php", "source_location": "L37"}, {"id": "traits_apipaginationtrait_getpaginationmeta", "label": "getPaginationMeta()", "file_type": "code", "source_file": "C:\\Users\\marce\\OneDrive\\Desktop\\PROJETOS WEB\\LOJA RATAPLAM\\Modules\\Core\\Traits\\ApiPaginationTrait.php", "source_location": "L45"}, {"id": "traits_apipaginationtrait_getpaginationlinks", "label": "getPaginationLinks()", "file_type": "code", "source_file": "C:\\Users\\marce\\OneDrive\\Desktop\\PROJETOS WEB\\LOJA RATAPLAM\\Modules\\Core\\Traits\\ApiPaginationTrait.php", "source_location": "L67"}, {"id": "traits_apipaginationtrait_getpaginationsummary", "label": "getPaginationSummary()", "file_type": "code", "source_file": "C:\\Users\\marce\\OneDrive\\Desktop\\PROJETOS WEB\\LOJA RATAPLAM\\Modules\\Core\\Traits\\ApiPaginationTrait.php", "source_location": "L97"}, {"id": "traits_apipaginationtrait_validatepaginationparams", "label": "validatePaginationParams()", "file_type": "code", "source_file": "C:\\Users\\marce\\OneDrive\\Desktop\\PROJETOS WEB\\LOJA RATAPLAM\\Modules\\Core\\Traits\\ApiPaginationTrait.php", "source_location": "L113"}, {"id": "traits_apipaginationtrait_getpaginationoptions", "label": "getPaginationOptions()", "file_type": "code", "source_file": "C:\\Users\\marce\\OneDrive\\Desktop\\PROJETOS WEB\\LOJA RATAPLAM\\Modules\\Core\\Traits\\ApiPaginationTrait.php", "source_location": "L127"}, {"id": "traits_apipaginationtrait_needspagination", "label": "needsPagination()", "file_type": "code", "source_file": "C:\\Users\\marce\\OneDrive\\Desktop\\PROJETOS WEB\\LOJA RATAPLAM\\Modules\\Core\\Traits\\ApiPaginationTrait.php", "source_location": "L139"}, {"id": "traits_apipaginationtrait_getoffset", "label": "getOffset()", "file_type": "code", "source_file": "C:\\Users\\marce\\OneDrive\\Desktop\\PROJETOS WEB\\LOJA RATAPLAM\\Modules\\Core\\Traits\\ApiPaginationTrait.php", "source_location": "L147"}, {"id": "traits_apipaginationtrait_calculatetotalpages", "label": "calculateTotalPages()", "file_type": "code", "source_file": "C:\\Users\\marce\\OneDrive\\Desktop\\PROJETOS WEB\\LOJA RATAPLAM\\Modules\\Core\\Traits\\ApiPaginationTrait.php", "source_location": "L155"}, {"id": "traits_apipaginationtrait_getpagerange", "label": "getPageRange()", "file_type": "code", "source_file": "C:\\Users\\marce\\OneDrive\\Desktop\\PROJETOS WEB\\LOJA RATAPLAM\\Modules\\Core\\Traits\\ApiPaginationTrait.php", "source_location": "L163"}], "edges": [{"source": "c_users_marce_onedrive_desktop_projetos_web_loja_rataplam_modules_core_traits_apipaginationtrait_php", "target": "builder", "relation": "imports", "context": "import", "confidence": "EXTRACTED", "source_file": "C:\\Users\\marce\\OneDrive\\Desktop\\PROJETOS WEB\\LOJA RATAPLAM\\Modules\\Core\\Traits\\ApiPaginationTrait.php", "source_location": "L7", "weight": 1.0}, {"source": "c_users_marce_onedrive_desktop_projetos_web_loja_rataplam_modules_core_traits_apipaginationtrait_php", "target": "request", "relation": "imports", "context": "import", "confidence": "EXTRACTED", "source_file": "C:\\Users\\marce\\OneDrive\\Desktop\\PROJETOS WEB\\LOJA RATAPLAM\\Modules\\Core\\Traits\\ApiPaginationTrait.php", "source_location": "L8", "weight": 1.0}, {"source": "c_users_marce_onedrive_desktop_projetos_web_loja_rataplam_modules_core_traits_apipaginationtrait_php", "target": "lengthawarepaginator", "relation": "imports", "context": "import", "confidence": "EXTRACTED", "source_file": "C:\\Users\\marce\\OneDrive\\Desktop\\PROJETOS WEB\\LOJA RATAPLAM\\Modules\\Core\\Traits\\ApiPaginationTrait.php", "source_location": "L9", "weight": 1.0}, {"source": "c_users_marce_onedrive_desktop_projetos_web_loja_rataplam_modules_core_traits_apipaginationtrait_php", "target": "traits_apipaginationtrait_paginatequery", "relation": "contains", "confidence": "EXTRACTED", "source_file": "C:\\Users\\marce\\OneDrive\\Desktop\\PROJETOS WEB\\LOJA RATAPLAM\\Modules\\Core\\Traits\\ApiPaginationTrait.php", "source_location": "L16", "weight": 1.0}, {"source": "c_users_marce_onedrive_desktop_projetos_web_loja_rataplam_modules_core_traits_apipaginationtrait_php", "target": "traits_apipaginationtrait_getperpage", "relation": "contains", "confidence": "EXTRACTED", "source_file": "C:\\Users\\marce\\OneDrive\\Desktop\\PROJETOS WEB\\LOJA RATAPLAM\\Modules\\Core\\Traits\\ApiPaginationTrait.php", "source_location": "L27", "weight": 1.0}, {"source": "c_users_marce_onedrive_desktop_projetos_web_loja_rataplam_modules_core_traits_apipaginationtrait_php", "target": "traits_apipaginationtrait_getpage", "relation": "contains", "confidence": "EXTRACTED", "source_file": "C:\\Users\\marce\\OneDrive\\Desktop\\PROJETOS WEB\\LOJA RATAPLAM\\Modules\\Core\\Traits\\ApiPaginationTrait.php", "source_location": "L37", "weight": 1.0}, {"source": "c_users_marce_onedrive_desktop_projetos_web_loja_rataplam_modules_core_traits_apipaginationtrait_php", "target": "traits_apipaginationtrait_getpaginationmeta", "relation": "contains", "confidence": "EXTRACTED", "source_file": "C:\\Users\\marce\\OneDrive\\Desktop\\PROJETOS WEB\\LOJA RATAPLAM\\Modules\\Core\\Traits\\ApiPaginationTrait.php", "source_location": "L45", "weight": 1.0}, {"source": "c_users_marce_onedrive_desktop_projetos_web_loja_rataplam_modules_core_traits_apipaginationtrait_php", "target": "traits_apipaginationtrait_getpaginationlinks", "relation": "contains", "confidence": "EXTRACTED", "source_file": "C:\\Users\\marce\\OneDrive\\Desktop\\PROJETOS WEB\\LOJA RATAPLAM\\Modules\\Core\\Traits\\ApiPaginationTrait.php", "source_location": "L67", "weight": 1.0}, {"source": "c_users_marce_onedrive_desktop_projetos_web_loja_rataplam_modules_core_traits_apipaginationtrait_php", "target": "traits_apipaginationtrait_getpaginationsummary", "relation": "contains", "confidence": "EXTRACTED", "source_file": "C:\\Users\\marce\\OneDrive\\Desktop\\PROJETOS WEB\\LOJA RATAPLAM\\Modules\\Core\\Traits\\ApiPaginationTrait.php", "source_location": "L97", "weight": 1.0}, {"source": "c_users_marce_onedrive_desktop_projetos_web_loja_rataplam_modules_core_traits_apipaginationtrait_php", "target": "traits_apipaginationtrait_validatepaginationparams", "relation": "contains", "confidence": "EXTRACTED", "source_file": "C:\\Users\\marce\\OneDrive\\Desktop\\PROJETOS WEB\\LOJA RATAPLAM\\Modules\\Core\\Traits\\ApiPaginationTrait.php", "source_location": "L113", "weight": 1.0}, {"source": "c_users_marce_onedrive_desktop_projetos_web_loja_rataplam_modules_core_traits_apipaginationtrait_php", "target": "traits_apipaginationtrait_getpaginationoptions", "relation": "contains", "confidence": "EXTRACTED", "source_file": "C:\\Users\\marce\\OneDrive\\Desktop\\PROJETOS WEB\\LOJA RATAPLAM\\Modules\\Core\\Traits\\ApiPaginationTrait.php", "source_location": "L127", "weight": 1.0}, {"source": "c_users_marce_onedrive_desktop_projetos_web_loja_rataplam_modules_core_traits_apipaginationtrait_php", "target": "traits_apipaginationtrait_needspagination", "relation": "contains", "confidence": "EXTRACTED", "source_file": "C:\\Users\\marce\\OneDrive\\Desktop\\PROJETOS WEB\\LOJA RATAPLAM\\Modules\\Core\\Traits\\ApiPaginationTrait.php", "source_location": "L139", "weight": 1.0}, {"source": "c_users_marce_onedrive_desktop_projetos_web_loja_rataplam_modules_core_traits_apipaginationtrait_php", "target": "traits_apipaginationtrait_getoffset", "relation": "contains", "confidence": "EXTRACTED", "source_file": "C:\\Users\\marce\\OneDrive\\Desktop\\PROJETOS WEB\\LOJA RATAPLAM\\Modules\\Core\\Traits\\ApiPaginationTrait.php", "source_location": "L147", "weight": 1.0}, {"source": "c_users_marce_onedrive_desktop_projetos_web_loja_rataplam_modules_core_traits_apipaginationtrait_php", "target": "traits_apipaginationtrait_calculatetotalpages", "relation": "contains", "confidence": "EXTRACTED", "source_file": "C:\\Users\\marce\\OneDrive\\Desktop\\PROJETOS WEB\\LOJA RATAPLAM\\Modules\\Core\\Traits\\ApiPaginationTrait.php", "source_location": "L155", "weight": 1.0}, {"source": "c_users_marce_onedrive_desktop_projetos_web_loja_rataplam_modules_core_traits_apipaginationtrait_php", "target": "traits_apipaginationtrait_getpagerange", "relation": "contains", "confidence": "EXTRACTED", "source_file": "C:\\Users\\marce\\OneDrive\\Desktop\\PROJETOS WEB\\LOJA RATAPLAM\\Modules\\Core\\Traits\\ApiPaginationTrait.php", "source_location": "L163", "weight": 1.0}, {"source": "traits_apipaginationtrait_paginatequery", "target": "traits_apipaginationtrait_getperpage", "relation": "calls", "context": "call", "confidence": "EXTRACTED", "source_file": "C:\\Users\\marce\\OneDrive\\Desktop\\PROJETOS WEB\\LOJA RATAPLAM\\Modules\\Core\\Traits\\ApiPaginationTrait.php", "source_location": "L18", "weight": 1.0}, {"source": "traits_apipaginationtrait_paginatequery", "target": "traits_apipaginationtrait_getpage", "relation": "calls", "context": "call", "confidence": "EXTRACTED", "source_file": "C:\\Users\\marce\\OneDrive\\Desktop\\PROJETOS WEB\\LOJA RATAPLAM\\Modules\\Core\\Traits\\ApiPaginationTrait.php", "source_location": "L19", "weight": 1.0}, {"source": "traits_apipaginationtrait_validatepaginationparams", "target": "traits_apipaginationtrait_getperpage", "relation": "calls", "context": "call", "confidence": "EXTRACTED", "source_file": "C:\\Users\\marce\\OneDrive\\Desktop\\PROJETOS WEB\\LOJA RATAPLAM\\Modules\\Core\\Traits\\ApiPaginationTrait.php", "source_location": "L115", "weight": 1.0}, {"source": "traits_apipaginationtrait_validatepaginationparams", "target": "traits_apipaginationtrait_getpage", "relation": "calls", "context": "call", "confidence": "EXTRACTED", "source_file": "C:\\Users\\marce\\OneDrive\\Desktop\\PROJETOS WEB\\LOJA RATAPLAM\\Modules\\Core\\Traits\\ApiPaginationTrait.php", "source_location": "L116", "weight": 1.0}], "raw_calls": [{"caller_nid": "traits_apipaginationtrait_paginatequery", "callee": "paginate", "is_member_call": true, "source_file": "C:\\Users\\marce\\OneDrive\\Desktop\\PROJETOS WEB\\LOJA RATAPLAM\\Modules\\Core\\Traits\\ApiPaginationTrait.php", "source_location": "L21"}, {"caller_nid": "traits_apipaginationtrait_getperpage", "callee": "get", "is_member_call": true, "source_file": "C:\\Users\\marce\\OneDrive\\Desktop\\PROJETOS WEB\\LOJA RATAPLAM\\Modules\\Core\\Traits\\ApiPaginationTrait.php", "source_location": "L29"}, {"caller_nid": "traits_apipaginationtrait_getperpage", "callee": "max", "is_member_call": false, "source_file": "C:\\Users\\marce\\OneDrive\\Desktop\\PROJETOS WEB\\LOJA RATAPLAM\\Modules\\Core\\Traits\\ApiPaginationTrait.php", "source_location": "L31"}, {"caller_nid": "traits_apipaginationtrait_getperpage", "callee": "min", "is_member_call": false, "source_file": "C:\\Users\\marce\\OneDrive\\Desktop\\PROJETOS WEB\\LOJA RATAPLAM\\Modules\\Core\\Traits\\ApiPaginationTrait.php", "source_location": "L31"}, {"caller_nid": "traits_apipaginationtrait_getpage", "callee": "max", "is_member_call": false, "source_file": "C:\\Users\\marce\\OneDrive\\Desktop\\PROJETOS WEB\\LOJA RATAPLAM\\Modules\\Core\\Traits\\ApiPaginationTrait.php", "source_location": "L39"}, {"caller_nid": "traits_apipaginationtrait_getpage", "callee": "get", "is_member_call": true, "source_file": "C:\\Users\\marce\\OneDrive\\Desktop\\PROJETOS WEB\\LOJA RATAPLAM\\Modules\\Core\\Traits\\ApiPaginationTrait.php", "source_location": "L39"}, {"caller_nid": "traits_apipaginationtrait_getpaginationmeta", "callee": "currentPage", "is_member_call": true, "source_file": "C:\\Users\\marce\\OneDrive\\Desktop\\PROJETOS WEB\\LOJA RATAPLAM\\Modules\\Core\\Traits\\ApiPaginationTrait.php", "source_location": "L48"}, {"caller_nid": "traits_apipaginationtrait_getpaginationmeta", "callee": "perPage", "is_member_call": true, "source_file": "C:\\Users\\marce\\OneDrive\\Desktop\\PROJETOS WEB\\LOJA RATAPLAM\\Modules\\Core\\Traits\\ApiPaginationTrait.php", "source_location": "L49"}, {"caller_nid": "traits_apipaginationtrait_getpaginationmeta", "callee": "total", "is_member_call": true, "source_file": "C:\\Users\\marce\\OneDrive\\Desktop\\PROJETOS WEB\\LOJA RATAPLAM\\Modules\\Core\\Traits\\ApiPaginationTrait.php", "source_location": "L50"}, {"caller_nid": "traits_apipaginationtrait_getpaginationmeta", "callee": "lastPage", "is_member_call": true, "source_file": "C:\\Users\\marce\\OneDrive\\Desktop\\PROJETOS WEB\\LOJA RATAPLAM\\Modules\\Core\\Traits\\ApiPaginationTrait.php", "source_location": "L51"}, {"caller_nid": "traits_apipaginationtrait_getpaginationmeta", "callee": "firstItem", "is_member_call": true, "source_file": "C:\\Users\\marce\\OneDrive\\Desktop\\PROJETOS WEB\\LOJA RATAPLAM\\Modules\\Core\\Traits\\ApiPaginationTrait.php", "source_location": "L52"}, {"caller_nid": "traits_apipaginationtrait_getpaginationmeta", "callee": "lastItem", "is_member_call": true, "source_file": "C:\\Users\\marce\\OneDrive\\Desktop\\PROJETOS WEB\\LOJA RATAPLAM\\Modules\\Core\\Traits\\ApiPaginationTrait.php", "source_location": "L53"}, {"caller_nid": "traits_apipaginationtrait_getpaginationmeta", "callee": "hasMorePages", "is_member_call": true, "source_file": "C:\\Users\\marce\\OneDrive\\Desktop\\PROJETOS WEB\\LOJA RATAPLAM\\Modules\\Core\\Traits\\ApiPaginationTrait.php", "source_location": "L54"}, {"caller_nid": "traits_apipaginationtrait_getpaginationmeta", "callee": "url", "is_member_call": true, "source_file": "C:\\Users\\marce\\OneDrive\\Desktop\\PROJETOS WEB\\LOJA RATAPLAM\\Modules\\Core\\Traits\\ApiPaginationTrait.php", "source_location": "L56"}, {"caller_nid": "traits_apipaginationtrait_getpaginationmeta", "callee": "url", "is_member_call": true, "source_file": "C:\\Users\\marce\\OneDrive\\Desktop\\PROJETOS WEB\\LOJA RATAPLAM\\Modules\\Core\\Traits\\ApiPaginationTrait.php", "source_location": "L57"}, {"caller_nid": "traits_apipaginationtrait_getpaginationmeta", "callee": "lastPage", "is_member_call": true, "source_file": "C:\\Users\\marce\\OneDrive\\Desktop\\PROJETOS WEB\\LOJA RATAPLAM\\Modules\\Core\\Traits\\ApiPaginationTrait.php", "source_location": "L57"}, {"caller_nid": "traits_apipaginationtrait_getpaginationmeta", "callee": "previousPageUrl", "is_member_call": true, "source_file": "C:\\Users\\marce\\OneDrive\\Desktop\\PROJETOS WEB\\LOJA RATAPLAM\\Modules\\Core\\Traits\\ApiPaginationTrait.php", "source_location": "L58"}, {"caller_nid": "traits_apipaginationtrait_getpaginationmeta", "callee": "nextPageUrl", "is_member_call": true, "source_file": "C:\\Users\\marce\\OneDrive\\Desktop\\PROJETOS WEB\\LOJA RATAPLAM\\Modules\\Core\\Traits\\ApiPaginationTrait.php", "source_location": "L59"}, {"caller_nid": "traits_apipaginationtrait_getpaginationlinks", "callee": "previousPageUrl", "is_member_call": true, "source_file": "C:\\Users\\marce\\OneDrive\\Desktop\\PROJETOS WEB\\LOJA RATAPLAM\\Modules\\Core\\Traits\\ApiPaginationTrait.php", "source_location": "L72"}, {"caller_nid": "traits_apipaginationtrait_getpaginationlinks", "callee": "previousPageUrl", "is_member_call": true, "source_file": "C:\\Users\\marce\\OneDrive\\Desktop\\PROJETOS WEB\\LOJA RATAPLAM\\Modules\\Core\\Traits\\ApiPaginationTrait.php", "source_location": "L73"}, {"caller_nid": "traits_apipaginationtrait_getpaginationlinks", "callee": "nextPageUrl", "is_member_call": true, "source_file": "C:\\Users\\marce\\OneDrive\\Desktop\\PROJETOS WEB\\LOJA RATAPLAM\\Modules\\Core\\Traits\\ApiPaginationTrait.php", "source_location": "L77"}, {"caller_nid": "traits_apipaginationtrait_getpaginationlinks", "callee": "nextPageUrl", "is_member_call": true, "source_file": "C:\\Users\\marce\\OneDrive\\Desktop\\PROJETOS WEB\\LOJA RATAPLAM\\Modules\\Core\\Traits\\ApiPaginationTrait.php", "source_location": "L78"}, {"caller_nid": "traits_apipaginationtrait_getpaginationlinks", "callee": "currentPage", "is_member_call": true, "source_file": "C:\\Users\\marce\\OneDrive\\Desktop\\PROJETOS WEB\\LOJA RATAPLAM\\Modules\\Core\\Traits\\ApiPaginationTrait.php", "source_location": "L82"}, {"caller_nid": "traits_apipaginationtrait_getpaginationlinks", "callee": "url", "is_member_call": true, "source_file": "C:\\Users\\marce\\OneDrive\\Desktop\\PROJETOS WEB\\LOJA RATAPLAM\\Modules\\Core\\Traits\\ApiPaginationTrait.php", "source_location": "L83"}, {"caller_nid": "traits_apipaginationtrait_getpaginationlinks", "callee": "currentPage", "is_member_call": true, "source_file": "C:\\Users\\marce\\OneDrive\\Desktop\\PROJETOS WEB\\LOJA RATAPLAM\\Modules\\Core\\Traits\\ApiPaginationTrait.php", "source_location": "L87"}, {"caller_nid": "traits_apipaginationtrait_getpaginationlinks", "callee": "lastPage", "is_member_call": true, "source_file": "C:\\Users\\marce\\OneDrive\\Desktop\\PROJETOS WEB\\LOJA RATAPLAM\\Modules\\Core\\Traits\\ApiPaginationTrait.php", "source_location": "L87"}, {"caller_nid": "traits_apipaginationtrait_getpaginationlinks", "callee": "url", "is_member_call": true, "source_file": "C:\\Users\\marce\\OneDrive\\Desktop\\PROJETOS WEB\\LOJA RATAPLAM\\Modules\\Core\\Traits\\ApiPaginationTrait.php", "source_location": "L88"}, {"caller_nid": "traits_apipaginationtrait_getpaginationlinks", "callee": "lastPage", "is_member_call": true, "source_file": "C:\\Users\\marce\\OneDrive\\Desktop\\PROJETOS WEB\\LOJA RATAPLAM\\Modules\\Core\\Traits\\ApiPaginationTrait.php", "source_location": "L88"}, {"caller_nid": "traits_apipaginationtrait_getpaginationsummary", "callee": "firstItem", "is_member_call": true, "source_file": "C:\\Users\\marce\\OneDrive\\Desktop\\PROJETOS WEB\\LOJA RATAPLAM\\Modules\\Core\\Traits\\ApiPaginationTrait.php", "source_location": "L99"}, {"caller_nid": "traits_apipaginationtrait_getpaginationsummary", "callee": "lastItem", "is_member_call": true, "source_file": "C:\\Users\\marce\\OneDrive\\Desktop\\PROJETOS WEB\\LOJA RATAPLAM\\Modules\\Core\\Traits\\ApiPaginationTrait.php", "source_location": "L100"}, {"caller_nid": "traits_apipaginationtrait_getpaginationsummary", "callee": "total", "is_member_call": true, "source_file": "C:\\Users\\marce\\OneDrive\\Desktop\\PROJETOS WEB\\LOJA RATAPLAM\\Modules\\Core\\Traits\\ApiPaginationTrait.php", "source_location": "L101"}, {"caller_nid": "traits_apipaginationtrait_calculatetotalpages", "callee": "ceil", "is_member_call": false, "source_file": "C:\\Users\\marce\\OneDrive\\Desktop\\PROJETOS WEB\\LOJA RATAPLAM\\Modules\\Core\\Traits\\ApiPaginationTrait.php", "source_location": "L157"}, {"caller_nid": "traits_apipaginationtrait_getpagerange", "callee": "currentPage", "is_member_call": true, "source_file": "C:\\Users\\marce\\OneDrive\\Desktop\\PROJETOS WEB\\LOJA RATAPLAM\\Modules\\Core\\Traits\\ApiPaginationTrait.php", "source_location": "L165"}, {"caller_nid": "traits_apipaginationtrait_getpagerange", "callee": "lastPage", "is_member_call": true, "source_file": "C:\\Users\\marce\\OneDrive\\Desktop\\PROJETOS WEB\\LOJA RATAPLAM\\Modules\\Core\\Traits\\ApiPaginationTrait.php", "source_location": "L166"}, {"caller_nid": "traits_apipaginationtrait_getpagerange", "callee": "max", "is_member_call": false, "source_file": "C:\\Users\\marce\\OneDrive\\Desktop\\PROJETOS WEB\\LOJA RATAPLAM\\Modules\\Core\\Traits\\ApiPaginationTrait.php", "source_location": "L168"}, {"caller_nid": "traits_apipaginationtrait_getpagerange", "callee": "min", "is_member_call": false, "source_file": "C:\\Users\\marce\\OneDrive\\Desktop\\PROJETOS WEB\\LOJA RATAPLAM\\Modules\\Core\\Traits\\ApiPaginationTrait.php", "source_location": "L169"}, {"caller_nid": "traits_apipaginationtrait_getpagerange", "callee": "range", "is_member_call": false, "source_file": "C:\\Users\\marce\\OneDrive\\Desktop\\PROJETOS WEB\\LOJA RATAPLAM\\Modules\\Core\\Traits\\ApiPaginationTrait.php", "source_location": "L171"}]}