{"nodes": [{"id": "c_users_marce_onedrive_desktop_projetos_web_loja_rataplam_modules_attribute_models_attribute_php", "label": "Attribute.php", "file_type": "code", "source_file": "C:\\Users\\marce\\OneDrive\\Desktop\\PROJETOS WEB\\LOJA RATAPLAM\\Modules\\Attribute\\Models\\Attribute.php", "source_location": "L1"}, {"id": "models_attribute_attribute", "label": "Attribute", "file_type": "code", "source_file": "C:\\Users\\marce\\OneDrive\\Desktop\\PROJETOS WEB\\LOJA RATAPLAM\\Modules\\Attribute\\Models\\Attribute.php", "source_location": "L52"}, {"id": "models_attribute_attribute_factory", "label": ".factory()", "file_type": "code", "source_file": "C:\\Users\\marce\\OneDrive\\Desktop\\PROJETOS WEB\\LOJA RATAPLAM\\Modules\\Attribute\\Models\\Attribute.php", "source_location": "L127"}, {"id": "models_attribute_attribute_groups", "label": ".groups()", "file_type": "code", "source_file": "C:\\Users\\marce\\OneDrive\\Desktop\\PROJETOS WEB\\LOJA RATAPLAM\\Modules\\Attribute\\Models\\Attribute.php", "source_location": "L135"}, {"id": "models_attribute_attribute_values", "label": ".values()", "file_type": "code", "source_file": "C:\\Users\\marce\\OneDrive\\Desktop\\PROJETOS WEB\\LOJA RATAPLAM\\Modules\\Attribute\\Models\\Attribute.php", "source_location": "L148"}, {"id": "models_attribute_attribute_attributevalues", "label": ".attributeValues()", "file_type": "code", "source_file": "C:\\Users\\marce\\OneDrive\\Desktop\\PROJETOS WEB\\LOJA RATAPLAM\\Modules\\Attribute\\Models\\Attribute.php", "source_location": "L159"}, {"id": "models_attribute_attribute_options", "label": ".options()", "file_type": "code", "source_file": "C:\\Users\\marce\\OneDrive\\Desktop\\PROJETOS WEB\\LOJA RATAPLAM\\Modules\\Attribute\\Models\\Attribute.php", "source_location": "L168"}, {"id": "models_attribute_attribute_getvaluecolumnname", "label": ".getValueColumnName()", "file_type": "code", "source_file": "C:\\Users\\marce\\OneDrive\\Desktop\\PROJETOS WEB\\LOJA RATAPLAM\\Modules\\Attribute\\Models\\Attribute.php", "source_location": "L177"}], "edges": [{"source": "c_users_marce_onedrive_desktop_projetos_web_loja_rataplam_modules_attribute_models_attribute_php", "target": "eloquent", "relation": "imports", "context": "import", "confidence": "EXTRACTED", "source_file": "C:\\Users\\marce\\OneDrive\\Desktop\\PROJETOS WEB\\LOJA RATAPLAM\\Modules\\Attribute\\Models\\Attribute.php", "source_location": "L7", "weight": 1.0}, {"source": "c_users_marce_onedrive_desktop_projetos_web_loja_rataplam_modules_attribute_models_attribute_php", "target": "builder", "relation": "imports", "context": "import", "confidence": "EXTRACTED", "source_file": "C:\\Users\\marce\\OneDrive\\Desktop\\PROJETOS WEB\\LOJA RATAPLAM\\Modules\\Attribute\\Models\\Attribute.php", "source_location": "L8", "weight": 1.0}, {"source": "c_users_marce_onedrive_desktop_projetos_web_loja_rataplam_modules_attribute_models_attribute_php", "target": "collection", "relation": "imports", "context": "import", "confidence": "EXTRACTED", "source_file": "C:\\Users\\marce\\OneDrive\\Desktop\\PROJETOS WEB\\LOJA RATAPLAM\\Modules\\Attribute\\Models\\Attribute.php", "source_location": "L9", "weight": 1.0}, {"source": "c_users_marce_onedrive_desktop_projetos_web_loja_rataplam_modules_attribute_models_attribute_php", "target": "belongstomany", "relation": "imports", "context": "import", "confidence": "EXTRACTED", "source_file": "C:\\Users\\marce\\OneDrive\\Desktop\\PROJETOS WEB\\LOJA RATAPLAM\\Modules\\Attribute\\Models\\Attribute.php", "source_location": "L10", "weight": 1.0}, {"source": "c_users_marce_onedrive_desktop_projetos_web_loja_rataplam_modules_attribute_models_attribute_php", "target": "hasmany", "relation": "imports", "context": "import", "confidence": "EXTRACTED", "source_file": "C:\\Users\\marce\\OneDrive\\Desktop\\PROJETOS WEB\\LOJA RATAPLAM\\Modules\\Attribute\\Models\\Attribute.php", "source_location": "L11", "weight": 1.0}, {"source": "c_users_marce_onedrive_desktop_projetos_web_loja_rataplam_modules_attribute_models_attribute_php", "target": "carbon", "relation": "imports", "context": "import", "confidence": "EXTRACTED", "source_file": "C:\\Users\\marce\\OneDrive\\Desktop\\PROJETOS WEB\\LOJA RATAPLAM\\Modules\\Attribute\\Models\\Attribute.php", "source_location": "L12", "weight": 1.0}, {"source": "c_users_marce_onedrive_desktop_projetos_web_loja_rataplam_modules_attribute_models_attribute_php", "target": "attributefactory", "relation": "imports", "context": "import", "confidence": "EXTRACTED", "source_file": "C:\\Users\\marce\\OneDrive\\Desktop\\PROJETOS WEB\\LOJA RATAPLAM\\Modules\\Attribute\\Models\\Attribute.php", "source_location": "L13", "weight": 1.0}, {"source": "c_users_marce_onedrive_desktop_projetos_web_loja_rataplam_modules_attribute_models_attribute_php", "target": "core", "relation": "imports", "context": "import", "confidence": "EXTRACTED", "source_file": "C:\\Users\\marce\\OneDrive\\Desktop\\PROJETOS WEB\\LOJA RATAPLAM\\Modules\\Attribute\\Models\\Attribute.php", "source_location": "L14", "weight": 1.0}, {"source": "c_users_marce_onedrive_desktop_projetos_web_loja_rataplam_modules_attribute_models_attribute_php", "target": "models_attribute_attribute", "relation": "contains", "confidence": "EXTRACTED", "source_file": "C:\\Users\\marce\\OneDrive\\Desktop\\PROJETOS WEB\\LOJA RATAPLAM\\Modules\\Attribute\\Models\\Attribute.php", "source_location": "L52", "weight": 1.0}, {"source": "models_attribute_attribute", "target": "models_attribute_attribute_factory", "relation": "method", "confidence": "EXTRACTED", "source_file": "C:\\Users\\marce\\OneDrive\\Desktop\\PROJETOS WEB\\LOJA RATAPLAM\\Modules\\Attribute\\Models\\Attribute.php", "source_location": "L127", "weight": 1.0}, {"source": "models_attribute_attribute", "target": "models_attribute_attribute_groups", "relation": "method", "confidence": "EXTRACTED", "source_file": "C:\\Users\\marce\\OneDrive\\Desktop\\PROJETOS WEB\\LOJA RATAPLAM\\Modules\\Attribute\\Models\\Attribute.php", "source_location": "L135", "weight": 1.0}, {"source": "models_attribute_attribute", "target": "models_attribute_attribute_values", "relation": "method", "confidence": "EXTRACTED", "source_file": "C:\\Users\\marce\\OneDrive\\Desktop\\PROJETOS WEB\\LOJA RATAPLAM\\Modules\\Attribute\\Models\\Attribute.php", "source_location": "L148", "weight": 1.0}, {"source": "models_attribute_attribute", "target": "models_attribute_attribute_attributevalues", "relation": "method", "confidence": "EXTRACTED", "source_file": "C:\\Users\\marce\\OneDrive\\Desktop\\PROJETOS WEB\\LOJA RATAPLAM\\Modules\\Attribute\\Models\\Attribute.php", "source_location": "L159", "weight": 1.0}, {"source": "models_attribute_attribute", "target": "models_attribute_attribute_options", "relation": "method", "confidence": "EXTRACTED", "source_file": "C:\\Users\\marce\\OneDrive\\Desktop\\PROJETOS WEB\\LOJA RATAPLAM\\Modules\\Attribute\\Models\\Attribute.php", "source_location": "L168", "weight": 1.0}, {"source": "models_attribute_attribute", "target": "models_attribute_attribute_getvaluecolumnname", "relation": "method", "confidence": "EXTRACTED", "source_file": "C:\\Users\\marce\\OneDrive\\Desktop\\PROJETOS WEB\\LOJA RATAPLAM\\Modules\\Attribute\\Models\\Attribute.php", "source_location": "L177", "weight": 1.0}], "raw_calls": [{"caller_nid": "models_attribute_attribute_factory", "callee": "AttributeFactory", "is_member_call": false, "source_file": "C:\\Users\\marce\\OneDrive\\Desktop\\PROJETOS WEB\\LOJA RATAPLAM\\Modules\\Attribute\\Models\\Attribute.php", "source_location": "L129"}, {"caller_nid": "models_attribute_attribute_groups", "callee": "belongsToMany", "is_member_call": true, "source_file": "C:\\Users\\marce\\OneDrive\\Desktop\\PROJETOS WEB\\LOJA RATAPLAM\\Modules\\Attribute\\Models\\Attribute.php", "source_location": "L137"}, {"caller_nid": "models_attribute_attribute_values", "callee": "hasMany", "is_member_call": true, "source_file": "C:\\Users\\marce\\OneDrive\\Desktop\\PROJETOS WEB\\LOJA RATAPLAM\\Modules\\Attribute\\Models\\Attribute.php", "source_location": "L151"}, {"caller_nid": "models_attribute_attribute_attributevalues", "callee": "hasMany", "is_member_call": true, "source_file": "C:\\Users\\marce\\OneDrive\\Desktop\\PROJETOS WEB\\LOJA RATAPLAM\\Modules\\Attribute\\Models\\Attribute.php", "source_location": "L162"}, {"caller_nid": "models_attribute_attribute_options", "callee": "hasMany", "is_member_call": true, "source_file": "C:\\Users\\marce\\OneDrive\\Desktop\\PROJETOS WEB\\LOJA RATAPLAM\\Modules\\Attribute\\Models\\Attribute.php", "source_location": "L171"}]}